pylenium/__init__.py
pylenium/a11y.py
pylenium/cdp.py
pylenium/config.py
pylenium/driver.py
pylenium/element.py
pylenium/jquery.py
pylenium/log.py
pylenium/performance.py
pylenium/scripts/__init__.py
pylenium/scripts/allure_reporting.py
pylenium/scripts/cli.py
pylenium/scripts/cli_utils.py
pylenium/scripts/conftest.py
pylenium/scripts/drag_and_drop.js
pylenium/scripts/load_jquery.js
pylenium/scripts/pylenium.json
pylenium/scripts/pytest.ini
pylenium/switch_to.py
pylenium/utils.py
pylenium/wait.py
pylenium/webdriver_factory.py
pyleniumio-1.21.0.dist-info/LICENSE
pyleniumio-1.21.0.dist-info/METADATA
pyleniumio-1.21.0.dist-info/WHEEL
pyleniumio-1.21.0.dist-info/entry_points.txt
pyleniumio-1.21.0.dist-info/RECORD
