Metadata-Version: 2.1
Name: pyleniumio
Version: 1.21.0
Summary: The best of Selenium and Cypress in a single Python Package
License: MIT
Author: Carlos
Author-email: carlos@qap.dev
Requires-Python: >=3.8.1
Classifier: License :: OSI Approved :: MIT License
Classifier: Programming Language :: Python :: 3
Classifier: Programming Language :: Python :: 3.9
Classifier: Programming Language :: Python :: 3.10
Classifier: Programming Language :: Python :: 3.11
Classifier: Programming Language :: Python :: 3.12
Requires-Dist: allure-pytest (>=2.13.2,<3.0.0)
Requires-Dist: axe-selenium-python (>=2.1.6,<3.0.0)
Requires-Dist: faker (>=23.1.0,<24.0.0)
Requires-Dist: pydantic (>=2.6.1,<3.0.0)
Requires-Dist: pytest (>=8.0.0,<9.0.0)
Requires-Dist: pytest-xdist (>=3.5.0,<4.0.0)
Requires-Dist: requests (>=2.31.0,<3.0.0)
Requires-Dist: selenium (>=4.17.2,<5.0.0)
Requires-Dist: typer[all] (>=0.9.0,<0.10.0)
